ldifj.py
ldifj-0.1.1.dist-info/LICENSE
ldifj-0.1.1.dist-info/METADATA
ldifj-0.1.1.dist-info/WHEEL
ldifj-0.1.1.dist-info/entry_points.txt
ldifj-0.1.1.dist-info/top_level.txt
ldifj-0.1.1.dist-info/RECORD
