Metadata-Version: 2.1
Name: ldifj
Version: 0.1.1
Summary: LDAP LDIF to JSON
Author-email: Philipp Schmitt <philipp@schmitt.co>
License: GNU GENERAL PUBLIC LICENSE
Keywords: ldap,ldif,json
Classifier: Programming Language :: Python :: 3
Requires-Python: >=3.9
License-File: LICENSE
Requires-Dist: python-ldap
Requires-Dist: rich
Requires-Dist: rich-argparse
